my_own_package/__init__.py
Aida_first_package-0.2.0.dist-info/METADATA
Aida_first_package-0.2.0.dist-info/WHEEL
Aida_first_package-0.2.0.dist-info/top_level.txt
Aida_first_package-0.2.0.dist-info/RECORD
