Metadata-Version: 2.1
Name: Aida-first-package
Version: 0.2.0
Summary: This is my first package.
Author: Aida
Author-email: radu.aida@yahoo.com
